ownlib/__init__.py
ownlib/class_person.py
ownlib/class_whatsapp_message.py
ownlib/doc/Readme_xml_lib.md
ownlib/functions_whatsapp_refueling.py
ownlib/months.py
ownlib/my_datalib.py
ownlib/my_fileio.py
ownlib/mytinylib.py
ownlib/one_s_uat_lib.py
ownlib/platon_settings.py
ownlib/settings/xml_settings.py
ownlib/txt_lib.py
ownlib/whapp_funcs.py
ownlib/xml_lib.py
ownlib-0.0.1b7.dist-info/LICENSE
ownlib-0.0.1b7.dist-info/METADATA
ownlib-0.0.1b7.dist-info/WHEEL
ownlib-0.0.1b7.dist-info/RECORD
