Metadata-Version: 2.1
Name: ownlib
Version: 0.0.1b7
Summary: Sample pypi project
License: GNU
Author: Андрей Мартынов
Author-email: real.cloudhunter@gmail.com
Requires-Python: >=3.11,<4.0
Classifier: License :: Other/Proprietary License
Classifier: Programming Language :: Python :: 3
Classifier: Programming Language :: Python :: 3.11
Classifier: Programming Language :: Python :: 3.12
Requires-Dist: ipython (>=8.22.1,<9.0.0)
Requires-Dist: loguru (>=0.7.2,<0.8.0)
Requires-Dist: pandas (>=2.2.1,<3.0.0)
